bridgelib/__init__.py
bridgelib/constants.py
bridgelib-0.1.1.dist-info/LICENSE.txt
bridgelib-0.1.1.dist-info/METADATA
bridgelib-0.1.1.dist-info/WHEEL
bridgelib-0.1.1.dist-info/top_level.txt
bridgelib-0.1.1.dist-info/RECORD
