Metadata-Version: 2.1
Name: bridgelib
Version: 0.1.1
Summary: Python Bridge Card Game library
Author: Wojciech Peisert
Author-email: wojtekp@sauron.pl
License: LICENCE.txt
License-File: LICENSE.txt
